[{"title":"The Latest in Pareidolia: Face In Tumour","post":"Haha, I heard this story the other day on the news. Maybe the image was just a reflection of the poor patient lying on the bed in agony. I’d assume a  testicular tumor may sometimes be painful, or maybe the docs just weren’t being gentle enough.\nR.\n\n","date":"November 5, 2011 at 1:46 pm","url":"https://shroudstory.com/2011/11/05/the-latest-in-pareidolia-face-in-tumour/","cat":"pareidolia","id":"comment-4598","author":"Ron","site":"shroudstory"}]
