[{"title":"The Metamorphosis and Manipulation of a Legend?","post":"An essential book, but the price amaze me. I bought it in its original Italian language and it is much cheaper.\n\n","date":"September 28, 2014 at 5:14 am","url":"https://shroudstory.com/2014/09/26/the-metamorphosis-and-manipulation-of-a-legend/","cat":"books","id":"comment-157414","author":"David Mo","site":"shroudstory"},{"title":"The Metamorphosis and Manipulation of a Legend?","post":"In fact, the only defect of this book is the price   :-)\n\n","date":"September 28, 2014 at 10:46 am","url":"https://shroudstory.com/2014/09/26/the-metamorphosis-and-manipulation-of-a-legend/","cat":"books","id":"comment-157467","author":"Andrea Nicolotti","site":"shroudstory"},{"title":"The Metamorphosis and Manipulation of a Legend?","post":"Had it been only, Andrea, had it…\n\n","date":"September 28, 2014 at 11:16 am","url":"https://shroudstory.com/2014/09/26/the-metamorphosis-and-manipulation-of-a-legend/","cat":"books","id":"comment-157472","author":"O.K.","site":"shroudstory"},{"title":"The Metamorphosis and Manipulation of a Legend?","post":"If someone desires to read it, large part of Andrea’s book is availale on Google Books:\nhttp://books.google.pl/books?id=W2HPBAAAQBAJ&pg=PA125&lpg=PA125&dq=Andrea+Nicolotti,+Lucca&source=bl&ots=JT6E7euHCg&sig=oBbggaE1fuJ83K4IZcJJBzuQFNA&hl=pl&sa=X&ei=LzRWVN34JsvZapPDgrAJ&ved=0CFEQ6AEwBg#v=onepage&q&f=false\n\n","date":"November 2, 2014 at 9:43 am","url":"https://shroudstory.com/2014/09/26/the-metamorphosis-and-manipulation-of-a-legend/","cat":"books","id":"comment-167897","author":"O.K.","site":"shroudstory"}]
