[{"id":"comment-10157","author":"peter_ford","post":"As far as i am concerned I have discovered an Australian film scientist who has solved the mystery of the Shroud of Turin by discovering the second Shroud check this out name is Vincenzo Giovanni Ruello. Using a simple film system he discovered the alive face of Christ in the St Peters Veronica Veil.","date":"2012-04-08","mins":"10:26 am","url":"https://shroudstory.com/2012/03/30/a-20000-shroud-of-turin-challenge-to-richard-dawkins/","cat":"carbon_14_dating","title":"A £20,000 Shroud of Turin Challenge to Richard Dawkins"}]
