[{"title":"Vatican Insider: The essence of religion meets human science","post":"I am not so much struck by the mass evidence of violence and crucifixion on the Shroud, but the look on the face.  It is not one of terror, fright, excruciating pain or anything of the like.  The face on the Shroud looks peaceful.\n\n","date":"March 27, 2013 at 8:36 pm","url":"https://shroudstory.com/2013/03/27/vatican-insider-the-essence-of-religion-meets-human-science/","cat":"history","id":"comment-28533","author":"Andy Weiss","site":"shroudstory"}]
