[{"title":"History in the Unmaking:  The Shroud of Joseph of Arimathea","post":"On August 25, 2014 at 1:36 pm\nIn Reply to Charles Freeman:\nCF:So what do you think about the legend that Belsdon Scott has in his book on the Shroud (pp.32- 33) that Patriarch Heraclius of Jerusalem gave the Shroud to the king of Cyprus in 1087 and it was kept on the island until the Turks overrran Cyprus. Then Margarite de Charny escaped with it and the reason that the Savoys were keen to have it was that the duke of Savoy’s wife Anne of Lusignan came from a family that had claimed stewardship of the holy places of Palestine as well as the crusader kingship of Jerusalem.\nAll quite plausible, don’t you think?\nMe:Plausible, yes. It is plausible that Shroud spent some time on Cyprus on one point of its complicated history -but not necessarily at the precise time and circumstances that legend says.\nWe will discuss it another time.\nhttp://en.wikipedia.org/wiki/Acheiropoietos_Monastery\nhttp://www.whatson-northcyprus.com/interest/kyrenia/akhiropiitos.htm\nI also recommend reading fascinating article MYSTERY OF THE MISSING MANDYLION\nby Ian Wilson from BSTS Newslettter no 36:\nhttp://www.shroud.com/pdfs/n36part5.pdf\nWho knows what interesting documents that may shed some light on complicated Shroud history (especially missing years 1205-1356) may be in that monastery…\n\n","date":"September 2, 2014 at 7:04 am","url":"https://shroudstory.com/2014/09/02/history-in-the-unmaking-the-shroud-of-joseph-of-arimathea/","cat":"history","id":"comment-148040","author":"O.K.","site":"shroudstory"},{"title":"History in the Unmaking:  The Shroud of Joseph of Arimathea","post":"The Templars were also in Cyprus.\n\n","date":"September 2, 2014 at 8:20 am","url":"https://shroudstory.com/2014/09/02/history-in-the-unmaking-the-shroud-of-joseph-of-arimathea/","cat":"history","id":"comment-148055","author":"Louis","site":"shroudstory"},{"title":"History in the Unmaking:  The Shroud of Joseph of Arimathea","post":"Exactly.\n\n","date":"September 2, 2014 at 8:28 am","url":"https://shroudstory.com/2014/09/02/history-in-the-unmaking-the-shroud-of-joseph-of-arimathea/","cat":"history","id":"comment-148056","author":"O.K.","site":"shroudstory"},{"title":"History in the Unmaking:  The Shroud of Joseph of Arimathea","post":"Heraclius, Patriarch of Jerusalem, consecrated the Templar (round) Church in London in honour of the Virgin Mary. See Part II, with photographs in:\n https://www.academia.edu/7556467/Jesus_was_not_buried_in_Talpiot_-_Parts_I_and_II\n\n","date":"September 2, 2014 at 8:42 am","url":"https://shroudstory.com/2014/09/02/history-in-the-unmaking-the-shroud-of-joseph-of-arimathea/","cat":"history","id":"comment-148059","author":"Louis","site":"shroudstory"}]
