[{"id":"comment-12396","author":"ironclad","post":"This also agrees with the Synoptics which use the singular in describing the main cloth..","date":"2012-06-13","mins":"11:25 am","url":"https://shroudstory.com/2012/05/29/new-dawkins-challenge-video/","cat":"carbon_14_dating","title":"New Dawkins Challenge Video"},{"id":"comment-12716","author":"ironclad","post":"He’s echoing the views of Wellhausen and company, a closeted group of German antisemites who hated everything Jewish, including their sacred books. See, I could play the game too..","date":"2012-06-19","mins":"2:14 pm","url":"https://shroudstory.com/2012/06/19/who-is-evolving-into-stupid/","cat":"carbon_14_dating","title":"Who is Evolving Into Stupid?"},{"id":"comment-12717","author":"ironclad","post":"Apparently, he is not aware that those antiquated books he is scorning have also been subjected to “years of careful research, analysis, reason, logic and a certain thing called ‘evidence,'” adding to and enhancing our knowledge of the ancient near east..","date":"2012-06-19","mins":"2:21 pm","url":"https://shroudstory.com/2012/06/19/who-is-evolving-into-stupid/","cat":"carbon_14_dating","title":"Who is Evolving Into Stupid?"}]
