[{"title":"The Mysteries of the Holy Sepulcher Documentary","post":"The 7Q5 at 0:41\n\n","date":"December 16, 2013 at 2:08 pm","url":"https://shroudstory.com/2013/12/16/the-mysteries-of-the-holy-sepulcher-documentary/","cat":"video","id":"comment-60403","author":"O.K.","site":"shroudstory"},{"title":"The Mysteries of the Holy Sepulcher Documentary","post":"I am looking forward to this program.\n\n","date":"December 16, 2013 at 2:51 pm","url":"https://shroudstory.com/2013/12/16/the-mysteries-of-the-holy-sepulcher-documentary/","cat":"video","id":"comment-60427","author":"ekmcmahon","site":"shroudstory"}]
