{"art":[{"author":"andy_hobelaid","post":"Go into all the world and preach the Good News to everyone.\nAnyone who believes and is baptized will be saved . But anyone who refuses to believe will be condemned.\nthese miraculous signs will accompany those who believe: They will cast out demons in my name, and they will speak in new languages.*\nThey will be able to handle snakes with safety, and if they drink anything poisonous, it won’t\nhurt them. They will be able to place their hands on the sick, and they will be healed.”\nMark 16:15:18\nHello , I am Andy Hobelaid, M.Photog.Cr.APPO.MPA.HLM.and so on, hahaha.\nI am a Commercial Studio Photography, 1977-?.\nIn May 13, 2001, Mother’s Day at 7:00 a.m. London University Hospital, I relay on bad news.\nI was 45 year young. Four days without sleep; yawn? 96 hours I spent time in Sarnia, On.\nthat where I was born, to finish the three jobs that we’re do; you guess it; on May 12, 2001.\nA 2100 sq. ft. Studio, (really, 5,000 sq. ft. that was crowd, 70 ft. x 210 ft,) it was on the drawing board, (I built two homes, the first one, 2,100 sq. ft. and the next, 4,500 sq.ft.)\nI was using that 2,400 sq.ft for living space.\nFinish that three jobs, nap time. Oh, I forgot to tell you; I lost my speech two days in?\nNo problems, I go to bed and I awake voice and all.\nTwo hours bed? I was awake and I never had this feeling be for?\nLondon is the place for me. May 13, 1:00 a.m. The Nurse,blood pressure reading;\n160 / 100? The Doctor, nice man, (physic wards?)  4:00 a.m. morphine high,\n(drugs, don’t use them.) 7:00 A.M. (I WAS STARING OUT OF A NICE DREAM!)\nAndy (” HOBI “) I got some bad new. You had a Major Stoke. “Is that all, hahaha.)\nO.K. (I said to myself?) Grad my pant and skirt; eh, (a Canadian term, I don’t use it,hahaha,)\nmy right arm; excuse me but I walk in with it, DID I NOT? My left arm working fine?\nHAY, MY RIGHT LEG, I SEE IT?\n It was five minutes, (morphine high,) mmm,  my work here is finish!\n8 years I could not talk.\nI look at the Computer, (1991-2001,) spell cat. qzw, cat?\nPlease excuse the writing spelling word?\nDay by day. 11 years, May 13, 2001.\nWhen the LORD Jesus had finished talking with them, he was taken up into heaven and sat down in the place of honor at God’s right hand.\nAnd the disciples went everywhere and preached, and the LORD worked through them, confirming what they said by many miraculous signs.\nMark 16:19:20\nGod Bless.\nAndy Hobelaid\nynda551@hotmail.ca\n\n","date":"April 8, 2012 at 11:25 pm","url":"https://shroudstory.com/2011/02/23/akianes-jesus-heaven-is-for-real-and-the-man-in-the-turin-shroud/","cat":"akiane_kramarik","title":"Akiane’s Jesus, Heaven is for Real and the Man in the Turin Shroud"}]}
