[{"id":"comment-16371","author":"tony","post":"Seems like the Shroud of Turin really keeps Colin Berry up at night..","date":"2012-09-17","mins":"1:45 am","url":"https://shroudstory.com/2012/09/16/better-than-david-rolfes-dawkins-challenge/","cat":"image_theory","title":"Better than David Rolfe’s Dawkins Challenge?"},{"id":"comment-16021","author":"tony","post":"I agree. Colin Berry should not be given much attention..","date":"2012-09-08","mins":"2:38 pm","url":"https://shroudstory.com/2012/09/08/wheres-the-evidence-colin/","cat":"image_theory","title":"Where’s the Evidence, Colin?"}]
