[{"title":"James Randi Visits the Shroud of Turin","post":"He went to see the “huge rag” with his head stuffed with all kinds of prejudice.\n\n","date":"May 9, 2015 at 5:55 pm","url":"https://shroudstory.com/2015/05/09/james-randi-visits-the-shroud-of-turin/","cat":"other_sites","id":"comment-198736","author":"Louis","site":"shroudstory"},{"title":"James Randi Visits the Shroud of Turin","post":"James Randi says:  “This huge rag.” \nMy reply to the “Amazing Randi.”     \nPoof, be gone!   :)\n\n","date":"May 9, 2015 at 8:04 pm","url":"https://shroudstory.com/2015/05/09/james-randi-visits-the-shroud-of-turin/","cat":"other_sites","id":"comment-198741","author":"Angel","site":"shroudstory"},{"title":"James Randi Visits the Shroud of Turin","post":"Archaeometry and Time:\nThe strange Case of “Turin Shroud Archaeometry” …\nSeventeen years and no one has been able to determine anything from the point of view of nanometric Research (see also: AFM controls…)!\nIn my opinion, this is the stunning fact, an incredible stop to the Archeometry\n(despite the interesting claims by Campanella and the attempts\nby prof. Giulio Fanti, etc., etc.)!\nNo true advances in archaeometric research … this is the sad situation (IMO).\n\n","date":"May 11, 2015 at 9:58 am","url":"https://shroudstory.com/2015/05/09/james-randi-visits-the-shroud-of-turin/","cat":"other_sites","id":"comment-198858","author":"piero","site":"shroudstory"},{"title":"James Randi Visits the Shroud of Turin","post":"Wasn’t there a prize of something like $20,000 for somebody to produce a duplicate of the shroud with certain authentic properties?  offered a few years ago I recall. Randi should have claimed it by now, eh?\n\n","date":"May 12, 2015 at 11:30 pm","url":"https://shroudstory.com/2015/05/09/james-randi-visits-the-shroud-of-turin/","cat":"other_sites","id":"comment-198975","author":"Matt Kowalski","site":"shroudstory"}]
