[{"title":"More Earths and Other Beings","post":"Do we not have enough to worry about here on our earth? I think if GOD wanted us to know if there were other planets that has life, HE would have told us so in the bible. I think too much money is being spent on unimportant things and we can’t even feed the poor. Come on now, do we really need to know about other planets? No. Do the hungry need to eat? Yes. So why don’t we stop looking for answers to questions that we are not suppose to know and get to feeding the hungry!\n\n","date":"February 2, 2011 at 6:51 am","url":"https://shroudstory.com/2011/01/31/more-earths-and-other-beings/","cat":"news_&_views","id":"comment-2331","author":"Sherry","site":"shroudstory"}]
