[{"title":"Black Thread","post":"Not a thread. Compare it to the fairly fine threads of the shroud that it is embedded into. It may be a fibre from a thread, or possibly a hair, but is far too thin to be in any way load-bearing.\n\n","date":"October 6, 2014 at 11:31 am","url":"https://shroudstory.com/2014/10/06/black-thread/","cat":"news_&_views","id":"comment-159837","author":"Hugh Farey","site":"shroudstory"},{"title":"Black Thread","post":"Red and blue silk? A black fibre? And in the sample area?  And this is called homogeneous?\n\n","date":"October 6, 2014 at 3:03 pm","url":"https://shroudstory.com/2014/10/06/black-thread/","cat":"news_&_views","id":"comment-159897","author":"daveb of wellington nz","site":"shroudstory"},{"title":"Black Thread","post":"The presence of a few strange fibers, in itself, has no significant effect on C14 dating. The important point is however, that they may indicate that the sample had been manipulated in the past.\n\n","date":"October 6, 2014 at 3:30 pm","url":"https://shroudstory.com/2014/10/06/black-thread/","cat":"news_&_views","id":"comment-159904","author":"O.K.","site":"shroudstory"}]
