[{"title":"Carl Jung and the Shroud of Turin","post":"An article this author wrote entitled “What did Jung see on the Shroud?” was posted on the Collegamento pro-Sindone website many years ago and has some useful details about what he thought about the relic as well as something on his religious beliefs.\n\n","date":"September 17, 2011 at 3:19 pm","url":"https://shroudstory.com/2011/09/15/carl-jung-and-the-shroud-of-turin/","cat":"news_&_views","id":"comment-3925","author":"Louis","site":"shroudstory"}]
