[{"title":"Quote for today by Paolo Di Lazzaro","post":"It is definitely not easy to replicate the body image all the more so when both pro forgery and pro miracle are both off track!\n\n","date":"January 22, 2012 at 6:26 pm","url":"https://shroudstory.com/2012/01/22/quote-for-today-by-paolo-di-lazzaro/","cat":"image_theory","id":"comment-7394","author":"Max Patrick Hamon","site":"shroudstory"},{"title":"Quote for today by Paolo Di Lazzaro","post":"We already knew that WELL BEFORE the ENEA did their experiments !!!\n\n","date":"January 23, 2012 at 12:43 pm","url":"https://shroudstory.com/2012/01/22/quote-for-today-by-paolo-di-lazzaro/","cat":"image_theory","id":"comment-7421","author":"Yannick Clément","site":"shroudstory"}]
