[{"id":"comment-503","author":"john_of_the_high_desert","post":"Which if you know anything about anything you would realize doesn’t look like a jew living in the holy land 2000 years ago. Clearly this image looks European. Several good Documentary type programs have shown this type of image to be a false image of Jesus..","date":"2009-05-23","mins":"7:02 am","url":"https://shroudstory.com/2009/02/20/the-artist-within-the-shroud-of-turin/","cat":"news_&_views","title":"The Artist Within & the Shroud of Turin"}]
