[{"title":"Shroud 4 Kids: Great Site","post":"What an awesome presentation. Petrus Soons and that photographer guy have made an invaluable contribution to the Shroud story.\n\n","date":"August 31, 2014 at 9:16 am","url":"https://shroudstory.com/2014/08/31/shroud-4-kids-great-site/","cat":"other_blogs","id":"comment-147539","author":"John Klotz","site":"shroudstory"},{"title":"Shroud 4 Kids: Great Site","post":"Yes indeed, and it is hosted out of New Mexico.  Good job Diane!\n\n","date":"August 31, 2014 at 10:16 am","url":"https://shroudstory.com/2014/08/31/shroud-4-kids-great-site/","cat":"other_blogs","id":"comment-147545","author":"Andy","site":"shroudstory"},{"title":"Shroud 4 Kids: Great Site","post":"Reminds one of the Hindu sadhus in India. No wonder Jesus is avatar in Hinduism.\n\n","date":"August 31, 2014 at 6:06 pm","url":"https://shroudstory.com/2014/08/31/shroud-4-kids-great-site/","cat":"other_blogs","id":"comment-147599","author":"Louis","site":"shroudstory"}]
