[{"id":"comment-213817","author":"dave_hines","post":"Hi Dcn Andy! Would you like to see up close and personal, live on video, exactly where they cut that sample? You are going to love this. The carbon dating is addressed right in the opening scene. Along with many other people you will be seeing The Shroud as it was in 1978, before it was cut. Every square inch of the Shroud. Slow pans. Enjoy the video. A little excitement in a otherwise dull day..","date":"2015-10-29","mins":"6:32 am","url":"https://shroudstory.com/2015/10/28/banding-proves-cloth-was-not-repaired/","cat":"guest_posting","title":"Banding Proves Cloth Was Not Repaired?"}]
